hexo2notionnext/__init__.py
hexo2notionnext/__main__.py
hexo2notionnext/hexo2notionnext.py
hexo2notionnext-0.0.9.dist-info/LICENSE
hexo2notionnext-0.0.9.dist-info/METADATA
hexo2notionnext-0.0.9.dist-info/WHEEL
hexo2notionnext-0.0.9.dist-info/entry_points.txt
hexo2notionnext-0.0.9.dist-info/top_level.txt
hexo2notionnext-0.0.9.dist-info/RECORD
