Metadata-Version: 2.1
Name: hexo2notionnext
Version: 0.0.9
Summary: Convert hexo  to notionnext
Home-page: https://github.com/zhangweidev/hexo2notionnext
Author: zhangwei
Author-email: chxxiu+dev@gmail.com
License: MIT
Keywords: hexo notion notion.so notion-py markdown md converter
Classifier: Development Status :: 5 - Production/Stable
Classifier: Intended Audience :: Developers
Classifier: License :: OSI Approved :: MIT License
Classifier: Programming Language :: Python :: 3.6
Classifier: Programming Language :: Python :: 3.7
Classifier: Programming Language :: Python :: 3.8
Classifier: Topic :: Office/Business :: News/Diary
Classifier: Topic :: System :: Filesystems
Classifier: Topic :: Text Processing :: Markup :: Markdown
Classifier: Topic :: Utilities
License-File: LICENSE
Requires-Dist: md2notion (>=2.4.1)
Requires-Dist: notion (>=0.0.28)
Requires-Dist: python-dateutil (>=2.8.2)
Requires-Dist: PyYAML (>=6.0)
